apply/__init__.py
apply/apply.py
apply-1.7.dist-info/LICENSE
apply-1.7.dist-info/METADATA
apply-1.7.dist-info/WHEEL
apply-1.7.dist-info/top_level.txt
apply-1.7.dist-info/RECORD
