Metadata-Version: 2.1
Name: apply
Version: 1.7
Summary: An apply function for Python 2 and 3
Home-page: https://github.com/stefanholek/apply
Author: Stefan H. Holek
Author-email: stefan@epy.co.at
License: BSD-2-Clause
Project-URL: Documentation, https://apply.readthedocs.io/en/stable/
Keywords: apply,read,write,property,properties
Classifier: Development Status :: 5 - Production/Stable
Classifier: Intended Audience :: Developers
Classifier: License :: OSI Approved :: BSD License
Classifier: Operating System :: OS Independent
Classifier: Programming Language :: Python
Classifier: Programming Language :: Python :: 2
Classifier: Programming Language :: Python :: 3
Requires-Python: !=3.0.*,!=3.1.*,!=3.2.*,!=3.3.*,>=2.7
License-File: LICENSE
Provides-Extra: docs
Requires-Dist: sphinx (==5.3.0) ; extra == 'docs'
Requires-Dist: sphinx-rtd-theme (==1.0.0) ; extra == 'docs'
